{
  "Python": {
    "row1": {
      "name": "脚本名(python)",
      "Introduction": "简介",
      "note": "备注",
      "view": "查看"
    },
    "script1": {
      "name": "基础数据转换",
      "Introduction": "用于基础数据的转换处理。",
      "note": "能够批量将同一文件夹下的xls文件转换为xlsx",
      "view": "/code.html?title=基础数据转换&file=/code/python/zhuanhuan.py"
    },
    "script2": {
      "name": "基础数据处理",
      "Introduction": "用于基础数据的转换处理，比基础数据转换高效",
      "note": "高效地批量将同一文件夹下的xls文件转换为xlsx，附带填写周报功能",
      "view": "/code.html?title=基础数据处理&file=/code/python/chuli.py"
    },
    "script3": {
      "name": "抢车票（普通版）",
      "Introduction": "普通版抢车票脚本。",
      "note": "适用于一般抢票需求。",
      "view": "/code.html?title=抢车票（普通版）&file=/code/python/qiangchepiao.py"
    },
    "script4": {
      "name": "抢车票（升级版）",
      "Introduction": "升级版抢车票脚本，功能更强大。",
      "note": "适用于高级抢票需求。",
      "view": "/code.html?title=抢车票（升级版）&file=/code/python/qiangchepiao1.py"
    },
    "script5": {
      "name": "进程管理",
      "Introduction": "用于管理计算机进程。",
      "note": "可精细的控制计算机上的进程、服务,附带映像劫持功能",
      "view": "/code.html?title=进程管理&file=/code/python/jincheng.py"
    },
    "script6": {
      "name": "多功能智能排序系统",
      "Introduction": "智能排序：一键排序，支持多种算法，文件导入",
      "note": "本程序集成多种算法,支持手动输入,文件导入,执行升序降序排列。",
      "view": "/code.html?title=多功能智能排序系统&file=/code/python/paixv.py"
    },
    "script7": {
      "name": "电脑锁定系统",
      "Introduction": "锁定电脑，防破解，密码解锁",
      "note": "本程序有一键锁定电脑，有动态密码验证，防止暴力破解，普通应用启动",
      "view": "/code.html?title=电脑锁定系统&file=/code/python/lockpc.py"
    },
    "script8": {
      "name": "图片裁剪合并专用",
      "Introduction": "可以对图片进行操作",
      "note": "本程序的功能为开发者设计，如有需求可自行修改使用",
      "view": "/code.html?title=图片裁剪合并专用&file=/code/python/image_process.py"
    }
  },
  "C++": {
    "row1": {
      "name": "脚本名(C++)",
      "Introduction": "简介",
      "note": "备注",
      "view": "查看"
    },
    "script1": {
      "name": "多功能智能排序系统",
      "Introduction": "智能排序：一键排序，支持多种算法，文件导入",
      "note": "本程序集成多种算法，支持手动输入与文件导入，自动执行升序降序排列。",
      "view": "/code.html?title=多功能智能排序系统&file=/code/cpp/paixv.cpp"
    }
  },
  "WebApp": {
    "row1": {
      "name": "网页小工具",
      "Introduction": "简介",
      "note": "备注",
      "view": "查看"
    },
    "tool1": {
      "name": "计算器",
      "Introduction": "简单的网页计算器",
      "note": "支持基本运算，科学运算，函数画图等这些功能，不需要下载，是网页计算的不错选择",
      "view": "/code/webapp/calculator"
    },
    "tool2": {
      "name": "基础数据转换（网页版）",
      "Introduction": "基础数据转换的网页版",
      "note": "比基础数据转换更快",
      "view": "/code/webapp/zhuanhuanhtml"
    },
    "tool3": {
      "name": "电脑解锁系统",
      "Introduction": "电脑锁定系统的动态密码生成器",
      "note": "可以实时生成动态密码给用户解锁",
      "view": "/code/webapp/unlockpc"
    },
    "tool4": {
      "name": "贪吃蛇",
      "Introduction": "一个网页版的贪吃蛇",
      "note": "可以在线游玩，无需下载，记录分数",
      "view": "/code/webapp/snakegame"
    },
    "tool5": {
      "name": "贪吃蛇双人版",
      "Introduction": "一个网页版的双人版贪吃蛇",
      "note": "可以在线游玩，无需下载，记录分数",
      "view": "/code/webapp/snakegamepro/snakegamepro.html"
    }
  }
}